aiida_quantum_transport/__init__.py
aiida_quantum_transport/helpers.py
aiida_quantum_transport/calculations/__init__.py
aiida_quantum_transport/calculations/base.py
aiida_quantum_transport/calculations/current.py
aiida_quantum_transport/calculations/custom.py
aiida_quantum_transport/calculations/dft.py
aiida_quantum_transport/calculations/dmft.py
aiida_quantum_transport/calculations/functions.py
aiida_quantum_transport/calculations/greens.py
aiida_quantum_transport/calculations/hybridize.py
aiida_quantum_transport/calculations/localize.py
aiida_quantum_transport/calculations/transmission.py
aiida_quantum_transport/cli/__init__.py
aiida_quantum_transport/cli/commands.py
aiida_quantum_transport/data/__init__.py
aiida_quantum_transport/data/custom.py
aiida_quantum_transport/parsers/__init__.py
aiida_quantum_transport/parsers/current.py
aiida_quantum_transport/parsers/custom.py
aiida_quantum_transport/parsers/dft.py
aiida_quantum_transport/parsers/dmft.py
aiida_quantum_transport/parsers/greens.py
aiida_quantum_transport/parsers/hybridize.py
aiida_quantum_transport/parsers/localize.py
aiida_quantum_transport/parsers/transmission.py
aiida_quantum_transport/workchains/__init__.py
aiida_quantum_transport/workchains/coulomb_diamonds.py
aiida_quantum_transport-0.1.0.dist-info/entry_points.txt
aiida_quantum_transport-0.1.0.dist-info/LICENSE
aiida_quantum_transport-0.1.0.dist-info/WHEEL
aiida_quantum_transport-0.1.0.dist-info/METADATA
aiida_quantum_transport-0.1.0.dist-info/RECORD
