Metadata-Version: 2.1
Name: aiida-quantum-transport
Version: 0.1.0
Summary: A plugin for quantum transport calculations based on NEGF methods.
Keywords: quantum,transport,NEGF,DMFT,aiida,plugin
Author-email: Edan Bainglass <edan.bainglass@gmail.com>
Requires-Python: >=3.9
Classifier: Programming Language :: Python
Classifier: Programming Language :: Python :: 3.9
Classifier: Programming Language :: Python :: 3.10
Classifier: Programming Language :: Python :: 3.11
Classifier: Programming Language :: Python :: 3.12
Classifier: Intended Audience :: Science/Research
Classifier: License :: OSI Approved :: MIT License
Classifier: Natural Language :: English
Classifier: Development Status :: 3 - Alpha
Classifier: Framework :: AiiDA
Requires-Dist: aiida-core>=2.0,<3
Requires-Dist: sphinx-design~=0.4.1 ; extra == "docs"
Requires-Dist: pydata-sphinx-theme==0.13.3 ; extra == "docs"
Requires-Dist: pre-commit~=2.2 ; extra == "pre-commit"
Requires-Dist: mypy~=1.7.1 ; extra == "pre-commit"
Requires-Dist: pytest~=7.0 ; extra == "testing"
Requires-Dist: pytest-cov~=2.7,<2.11 ; extra == "testing"
Requires-Dist: coverage~=6.0 ; extra == "testing"
Project-URL: Source, https://github.com/edan-bainglass/aiida-quantum-transport
Provides-Extra: docs
Provides-Extra: pre-commit
Provides-Extra: testing
